{"nodes": [{"id": "readme_pickleball_hub", "label": "PickleballHub", "file_type": "document", "source_file": "README.md", "source_location": null, "source_url": null, "captured_at": null, "author": null, "contributor": null}, {"id": "readme_flask_app", "label": "Flask Web Application", "file_type": "rationale", "source_file": "README.md", "source_location": null, "source_url": null, "captured_at": null, "author": null, "contributor": null}, {"id": "readme_supabase", "label": "Supabase Auth & Database", "file_type": "rationale", "source_file": "README.md", "source_location": null, "source_url": null, "captured_at": null, "author": null, "contributor": null}, {"id": "readme_vercel", "label": "Vercel Deployment", "file_type": "rationale", "source_file": "README.md", "source_location": null, "source_url": null, "captured_at": null, "author": null, "contributor": null}, {"id": "readme_session_auth", "label": "Session-Based Authentication", "file_type": "rationale", "source_file": "README.md", "source_location": null, "source_url": null, "captured_at": null, "author": null, "contributor": null}, {"id": "readme_blueprint_pattern", "label": "Flask Blueprint Pattern", "file_type": "rationale", "source_file": "README.md", "source_location": null, "source_url": null, "captured_at": null, "author": null, "contributor": null}], "edges": [{"source": "readme_pickleball_hub", "target": "readme_flask_app", "relation": "references", "confidence": "EXTRACTED", "confidence_score": 1.0, "source_file": "README.md", "source_location": null, "weight": 1.0}, {"source": "readme_pickleball_hub", "target": "readme_supabase", "relation": "references", "confidence": "EXTRACTED", "confidence_score": 1.0, "source_file": "README.md", "source_location": null, "weight": 1.0}, {"source": "readme_pickleball_hub", "target": "readme_vercel", "relation": "references", "confidence": "EXTRACTED", "confidence_score": 1.0, "source_file": "README.md", "source_location": null, "weight": 1.0}, {"source": "readme_pickleball_hub", "target": "readme_session_auth", "relation": "references", "confidence": "EXTRACTED", "confidence_score": 1.0, "source_file": "README.md", "source_location": null, "weight": 1.0}, {"source": "readme_pickleball_hub", "target": "readme_blueprint_pattern", "relation": "references", "confidence": "EXTRACTED", "confidence_score": 1.0, "source_file": "README.md", "source_location": null, "weight": 1.0}, {"source": "readme_supabase", "target": "init_supabase_client", "relation": "references", "confidence": "INFERRED", "confidence_score": 0.95, "source_file": "README.md", "source_location": null, "weight": 1.0}, {"source": "readme_blueprint_pattern", "target": "auth_blueprint", "relation": "references", "confidence": "INFERRED", "confidence_score": 0.95, "source_file": "README.md", "source_location": null, "weight": 1.0}], "hyperedges": []}