{"nodes": [{"id": "c_users_denn_desktop_pickleballhub_scratch_test_community_post_py", "label": "test_community_post.py", "file_type": "code", "source_file": "C:\\Users\\Denn\\Desktop\\PickleballHub\\scratch\\test_community_post.py", "source_location": "L1"}], "edges": [{"source": "c_users_denn_desktop_pickleballhub_scratch_test_community_post_py", "target": "os", "relation": "imports", "context": "import", "confidence": "EXTRACTED", "source_file": "C:\\Users\\Denn\\Desktop\\PickleballHub\\scratch\\test_community_post.py", "source_location": "L1", "weight": 1.0}, {"source": "c_users_denn_desktop_pickleballhub_scratch_test_community_post_py", "target": "sys", "relation": "imports", "context": "import", "confidence": "EXTRACTED", "source_file": "C:\\Users\\Denn\\Desktop\\PickleballHub\\scratch\\test_community_post.py", "source_location": "L2", "weight": 1.0}, {"source": "c_users_denn_desktop_pickleballhub_scratch_test_community_post_py", "target": "dotenv", "relation": "imports_from", "context": "import", "confidence": "EXTRACTED", "source_file": "C:\\Users\\Denn\\Desktop\\PickleballHub\\scratch\\test_community_post.py", "source_location": "L5", "weight": 1.0}, {"source": "c_users_denn_desktop_pickleballhub_scratch_test_community_post_py", "target": "supabase", "relation": "imports_from", "context": "import", "confidence": "EXTRACTED", "source_file": "C:\\Users\\Denn\\Desktop\\PickleballHub\\scratch\\test_community_post.py", "source_location": "L8", "weight": 1.0}], "raw_calls": []}